usergen/__init__.py
usergen/randomuser.py
randusergen-0.0.1.dist-info/LICENCE.txt
randusergen-0.0.1.dist-info/METADATA
randusergen-0.0.1.dist-info/WHEEL
randusergen-0.0.1.dist-info/top_level.txt
randusergen-0.0.1.dist-info/RECORD
