Metadata-Version: 2.1
Name: randusergen
Version: 0.0.1
Summary: This library enables the generation of up to 5000 random user data using the RandomUser API and stores it.
Home-page: https://github.com/codewithwan/randusergen
Author: codewithwan
Author-email: <deezerxstore@gmail.com>
License: MIT
Keywords: random,user,generator
Classifier: Development Status :: 1 - Planning
License-File: LICENCE.txt
